beaniekeyset/__init__.py
beaniekeyset/cursor.py
beaniekeyset/paging.py
beaniekeyset/serializer.py
beaniekeyset-0.3.0.dist-info/WHEEL
beaniekeyset-0.3.0.dist-info/METADATA
beaniekeyset-0.3.0.dist-info/RECORD
