Metadata-Version: 2.1
Name: beaniekeyset
Version: 0.3.0
Summary: 
Author: vamshi.aruru
Author-email: vamshi.aruru@virgodesigns.ai
Requires-Python: >=3.9,<4.0
Classifier: Programming Language :: Python :: 3
Classifier: Programming Language :: Python :: 3.10
Classifier: Programming Language :: Python :: 3.9
Requires-Dist: beanie (>=1.12.0,<2.0.0)
Requires-Dist: pydantic[all] (>=1.10.2,<2.0.0)
Requires-Dist: python-dateutil (>=2.8.2,<3.0.0)
